Metadata-Version: 1.1
Name: py-sony-bravia-remote
Version: 1.1
Summary: Library for remotely interfacing with Sony Bravia TV's.
Home-page: https://github.com/Photonios/py-sony-bravia-remote
Author: Swen Kooij
Author-email: swenkooij@gmail.com
License: MIT License
Keywords: sony,bravia,remote
Platform: UNKNOWN
Classifier: Intended Audience :: Developers
Classifier: License :: OSI Approved :: MIT License
Classifier: Operating System :: OS Independent
Classifier: Programming Language :: Python
Classifier: Programming Language :: Python :: 3.5
Classifier: Topic :: Internet :: WWW/HTTP
Classifier: Topic :: Internet :: WWW/HTTP :: Dynamic Content
